databricks_mosaic_gdal/__init__.py
databricks_mosaic_gdal/resources/gdal-3.4.3-filetree.tar.xz
databricks_mosaic_gdal/resources/gdal-3.4.3-symlinks.tar.xz
databricks_mosaic_gdal/resources/scripts/mosaic-gdal-3.4.3-filetree-init.sh
databricks_mosaic_gdal-3.4.3.post3.dist-info/LICENSE
databricks_mosaic_gdal-3.4.3.post3.dist-info/METADATA
databricks_mosaic_gdal-3.4.3.post3.dist-info/WHEEL
databricks_mosaic_gdal-3.4.3.post3.dist-info/top_level.txt
databricks_mosaic_gdal-3.4.3.post3.dist-info/RECORD
