Metadata-Version: 2.1
Name: databricks-mosaic-gdal
Version: 3.4.3.post3
Summary: GDAL install with Java Bindings for Databricks Runtime 11+
Home-page: https://github.com/databrickslabs/mosaic/tree/main/modules/python/gdal_package
Author: Databricks
License: Databricks License
Classifier: License :: Other/Proprietary License
Classifier: Topic :: Scientific/Engineering :: GIS
Classifier: Operating System :: POSIX :: Linux
Classifier: Programming Language :: Python
Classifier: Programming Language :: Python :: 3
Classifier: Programming Language :: Python :: 3.7
Classifier: Programming Language :: C
Classifier: Programming Language :: C++
Classifier: Programming Language :: Java
Requires-Python: >=3.7.0
License-File: LICENSE
